{
  "top_logic": [
    {
      "layer": 26,
      "type": "mlp",
      "score": 0.6094127189928573
    },
    {
      "layer": 26,
      "type": "attn",
      "score": 0.4214611830597533
    },
    {
      "layer": 34,
      "type": "mlp",
      "score": 0.3225953257035877
    },
    {
      "layer": 30,
      "type": "mlp",
      "score": 0.28440459486579794
    },
    {
      "layer": 24,
      "type": "attn",
      "score": 0.2798553461126928
    },
    {
      "layer": 31,
      "type": "mlp",
      "score": 0.2287129396550766
    },
    {
      "layer": 27,
      "type": "mlp",
      "score": 0.21894896680225598
    },
    {
      "layer": 18,
      "type": "mlp",
      "score": 0.1851704771865637
    },
    {
      "layer": 16,
      "type": "mlp",
      "score": 0.17747267389827256
    },
    {
      "layer": 17,
      "type": "mlp",
      "score": 0.16852010848140436
    },
    {
      "layer": 23,
      "type": "mlp",
      "score": 0.16001793976017373
    },
    {
      "layer": 15,
      "type": "attn",
      "score": 0.15617511369777048
    },
    {
      "layer": 20,
      "type": "mlp",
      "score": 0.143324229111518
    },
    {
      "layer": 14,
      "type": "mlp",
      "score": 0.1374843575909163
    },
    {
      "layer": 21,
      "type": "attn",
      "score": 0.1360371562865084
    },
    {
      "layer": 15,
      "type": "mlp",
      "score": 0.13026861992856048
    }
  ],
  "top_content": [
    {
      "layer": 26,
      "type": "attn",
      "score": 0.7211809547956953
    },
    {
      "layer": 26,
      "type": "mlp",
      "score": 0.6952541393934638
    },
    {
      "layer": 31,
      "type": "mlp",
      "score": 0.4679901430032092
    },
    {
      "layer": 24,
      "type": "attn",
      "score": 0.3045383214203385
    },
    {
      "layer": 27,
      "type": "mlp",
      "score": 0.2730161447237038
    },
    {
      "layer": 20,
      "type": "attn",
      "score": 0.27026737409577134
    },
    {
      "layer": 23,
      "type": "attn",
      "score": 0.23785442252897734
    },
    {
      "layer": 15,
      "type": "attn",
      "score": 0.2303276661520467
    },
    {
      "layer": 19,
      "type": "mlp",
      "score": 0.21739316387037064
    },
    {
      "layer": 16,
      "type": "attn",
      "score": 0.1934749920861032
    },
    {
      "layer": 13,
      "type": "mlp",
      "score": 0.18798594556531065
    },
    {
      "layer": 25,
      "type": "attn",
      "score": 0.16680016374557605
    },
    {
      "layer": 25,
      "type": "mlp",
      "score": 0.1640978539749349
    },
    {
      "layer": 27,
      "type": "attn",
      "score": 0.1369553249692623
    },
    {
      "layer": 8,
      "type": "mlp",
      "score": 0.13444187242798358
    },
    {
      "layer": 14,
      "type": "mlp",
      "score": 0.12885978769012063
    }
  ]
}